<?xml version="1.0" encoding="UTF-8"?>
<con:resource name="" path="testUlong" id="d9e03173-a209-482f-86c4-a02e4ef5a450" xmlns:xsi="http://www.w3.org/2001/XMLSchema-instance" xmlns:con="http://eviware.com/soapui/config">
  <con:settings>
    <con:setting id="d9e03173-a209-482f-86c4-a02e4ef5a450fileName">testUlong</con:setting>
  </con:settings>
  <con:parameters/>
  <con:method name="" id="18fedf4f-d1e4-4653-8124-e40f3ffb8348" method="GET">
    <con:settings/>
    <con:parameters>
      <con:parameter>
        <con:name>t</con:name>
        <con:value xsi:nil="true"/>
        <con:style>QUERY</con:style>
        <con:type xmlns:xs="http://www.w3.org/2001/XMLSchema">xs:integer</con:type>
        <con:default xsi:nil="true"/>
      </con:parameter>
    </con:parameters>
    <con:request name="Request 1" id="2a6e0660-2801-4e7c-92d2-49da6213421f" mediaType="application/json">
      <con:settings/>
      <con:endpoint>http://rapis02.aqa.com.ru</con:endpoint>
      <con:credentials>
        <con:selectedAuthProfile>No Authorization</con:selectedAuthProfile>
        <con:authType>No Authorization</con:authType>
      </con:credentials>
      <con:parameters/>
    </con:request>
  </con:method>
</con:resource>
