<?xml version="1.0" encoding="UTF-8"?>
<con:resource name="" path="testClassTransferArray" id="790d838c-057e-43dd-8b85-3f37b5d93858" xmlns:xsi="http://www.w3.org/2001/XMLSchema-instance" xmlns:con="http://eviware.com/soapui/config">
  <con:settings>
    <con:setting id="790d838c-057e-43dd-8b85-3f37b5d93858fileName">testClassTransferArray</con:setting>
  </con:settings>
  <con:parameters/>
  <con:method name="" id="9507e70a-78ec-41d5-8a64-9381b222a10c" method="POST">
    <con:settings/>
    <con:parameters/>
    <con:request name="Request 1" id="c9fbdb6d-0e00-4e8f-9bd3-da062850e81b" mediaType="application/json">
      <con:settings/>
      <con:endpoint>http://rapis02.aqa.com.ru</con:endpoint>
      <con:credentials>
        <con:selectedAuthProfile>No Authorization</con:selectedAuthProfile>
        <con:authType>No Authorization</con:authType>
      </con:credentials>
      <con:parameters/>
    </con:request>
  </con:method>
</con:resource>
